sequana/G4hunter.py
sequana/__init__.py
sequana/annotation.py
sequana/assembly.py
sequana/bamtools.py
sequana/bed.py
sequana/bedtools.py
sequana/biomol.py
sequana/blast.py
sequana/canu_scanner.py
sequana/checkm.py
sequana/cigar.py
sequana/cnv.py
sequana/codecs/__init__.py
sequana/codecs/embl_to_fasta.py
sequana/codon.py
sequana/compare.py
sequana/contigs.py
sequana/coverage.py
sequana/cpg_islands.py
sequana/criteria.py
sequana/cruciforms.py
sequana/cython/__init__.py
sequana/cython/g4hunter.pyx
sequana/cython/setup.py
sequana/databases.py
sequana/datatools.py
sequana/demultiplex.py
sequana/enrichment/__init__.py
sequana/enrichment/gsea.py
sequana/enrichment/kegg.py
sequana/enrichment/mart.py
sequana/enrichment/ontology.py
sequana/enrichment/panther.py
sequana/enrichment/plot_go_terms.py
sequana/enrichment/quickgo.py
sequana/enrichment/uniprot_enrichment.py
sequana/errors.py
sequana/fasta.py
sequana/fasta_gff_correction.py
sequana/fastq.py
sequana/fastq_splitter.py
sequana/fastqc.py
sequana/featurecounts.py
sequana/find_motif.py
sequana/freebayes_vcf_filter.py
sequana/frip.py
sequana/genbank.py
sequana/gfa.py
sequana/gff3.py
sequana/gtf_fixer.py
sequana/hmmtools.py
sequana/homer.py
sequana/idr.py
sequana/iem.py
sequana/imotif.py
sequana/isoseq.py
sequana/itol.py
sequana/iuapc.py
sequana/kegg.py
sequana/kmer.py
sequana/kozak.py
sequana/kraken/__init__.py
sequana/kraken/analysis.py
sequana/kraken/consensus.py
sequana/kraken/downloads.py
sequana/kraken/multikraken.py
sequana/kraken/sequential.py
sequana/krona.py
sequana/laa.py
sequana/lazy.py
sequana/lazyimports.py
sequana/macs3.py
sequana/metrics.py
sequana/mgi.py
sequana/mh.py
sequana/misc.py
sequana/mixture.py
sequana/modules_report/__init__.py
sequana/modules_report/bamqc.py
sequana/modules_report/base_module.py
sequana/modules_report/bwa_bam_to_fastq.py
sequana/modules_report/coverage.py
sequana/modules_report/cutadapt.py
sequana/modules_report/fastq_stats.py
sequana/modules_report/fastqc.py
sequana-0.19.6.dist-info/LICENSE
sequana-0.19.6.dist-info/METADATA
sequana-0.19.6.dist-info/WHEEL
sequana-0.19.6.dist-info/entry_points.txt
sequana-0.19.6.dist-info/RECORD
