Metadata-Version: 2.3
Name: sequana
Version: 0.19.6
Summary: A set of standalone application and pipelines dedicated to NGS analysis
License: BSD 3-Clause License
Keywords: snakemake,sequana,NGS
Author: Thomas Cokelaer
Author-email: <thomas.cokelaer@pasteur.fr>
Requires-Python: >=3.10,<4.0
Classifier: Development Status :: 5 - Production/Stable
Classifier: Intended Audience :: Education
Classifier: Intended Audience :: End Users/Desktop
Classifier: Intended Audience :: Developers
Classifier: Intended Audience :: Science/Research
Classifier: License :: OSI Approved :: BSD License
Classifier: Operating System :: POSIX :: Linux
Classifier: Programming Language :: Python :: 3.10
Classifier: Programming Language :: Python :: 3.11
Classifier: Programming Language :: Python :: 3.12
Classifier: Topic :: Software Development :: Libraries :: Python Modules
Classifier: Topic :: Scientific/Engineering :: Bio-Informatics
Classifier: Topic :: Scientific/Engineering :: Information Analysis
Requires-Dist: adjusttext (>=1.3.0,<2.0.0)
Requires-Dist: aiohttp (>=3.11.11,<4.0.0)
Requires-Dist: bioservices (>=1.11.2,<2.0.0)
Requires-Dist: brokenaxes (>=0.6.2,<0.7.0)
Requires-Dist: bx-python (>=0.13.0,<0.14.0)
Requires-Dist: click (>=8.1.8,<9.0.0)
Requires-Dist: colorlog (>=6.9.0)
Requires-Dist: colormap (>=1.2.0)
Requires-Dist: cython (>=3.0.11)
Requires-Dist: deprecated (>=1.2.15)
Requires-Dist: easydev (>=0.12.1)
Requires-Dist: gseapy (>=1.1.4)
Requires-Dist: itolapi (>=4.1.5)
Requires-Dist: kaleido (>=0.1)
Requires-Dist: matplotlib (>3)
Requires-Dist: multiqc (>=1.18,<=1.27)
Requires-Dist: natsort (>=8.4.0)
Requires-Dist: numpy (>=2.2.3)
Requires-Dist: pandas (>=2.2.3)
Requires-Dist: plotly (>=5.24.1)
Requires-Dist: pulp (<2.8.0)
Requires-Dist: pysam (>=0.22.1)
Requires-Dist: rich-click (>=1.7.2)
Requires-Dist: scikit-learn (>=1.6.1)
Requires-Dist: scipy (>=1.14)
Requires-Dist: seaborn (>=0.13.2)
Requires-Dist: selenium (>=4.28.0,<5.0.0)
Requires-Dist: snakemake (<8)
Requires-Dist: statsmodels (>=0.14)
Requires-Dist: tqdm (>=4.66.1)
Requires-Dist: upsetplot (>=0.9.0)
Requires-Dist: vcfpy (>=0.13.8)
Requires-Dist: xlrd (>=2.0)
Project-URL: Documentation, https://sequana.readthedocs.io
Project-URL: Homepage, https://sequana.readthedocs.io
Project-URL: Issues, https://github.com/sequana/sequana/issues
Project-URL: Repository, https://github.com/sequana/sequana
